{
  "timestamp": "2026-03-16T07:36:59.360Z",
  "practiceVerdict": "判定中です...",
  "testVerdict": "判定中です...",
  "historyCount": 0,
  "downloadCount": 2,
  "severeErrors": [],
  "sampleLogs": [
    {
      "type": "log",
      "text": "[OCR][Practice] start {kind: single, canvas: Object}"
    },
    {
      "type": "log",
      "text": "[TestCanvas] after initCanvas {canvasClient: Object, canvasIntrinsic: Object, wrapClient: Object}"
    },
    {
      "type": "log",
      "text": "[TestCanvas] showCurrentQuestion {canvasClient: Object, canvasIntrinsic: Object, wrapClient: Object}"
    },
    {
      "type": "log",
      "text": "[OCR][Test] start {kind: multi, boxIndex: 0, canvas: Object}"
    },
    {
      "type": "log",
      "text": "[OCR][Test] start {kind: multi, boxIndex: 1, canvas: Object}"
    }
  ]
}